<?xml version="1.0"?>
<resource xmlns:dcite="http://datacite.org/schema/kernel-3" xmlns:xsi="http://www.w3.org/2001/XMLSchema-instance" xsi:schemaLocation="http://datacite.org/schema/kernel-3 http://schema.datacite.org/meta/kernel-3/metadata.xsd">
  <identifier identifierType="DOI">10.1594/IEDA/100504</identifier>
  <creators>
    <creator>
      <creatorName>Borisov, O. G.</creatorName>
    </creator>
    <creator>
      <creatorName>Nikitina, I. B.</creatorName>
    </creator>
  </creators>
  <titles>
    <title>State of fumaroles at Shiveluch and Bezymianny volcanoes in 1960 (Russia)</title>
  </titles>
  <publisher>Integrated Earth Data Applications (IEDA)</publisher>
  <publicationYear>2014</publicationYear>
  <subjects>
    <subject subjectScheme="ECL">Chemistry:Gas</subject>
  </subjects>
  <dates>
    <date dateType="Available">2014-12-15</date>
  </dates>
  <language>eng</language>
  <resourceType resourceTypeGeneral="Dataset"/>
  <alternateIdentifiers>
    <alternateIdentifier alternateIdentifierType="URL">http://www.earthchem.org/library/browse/view?id=819</alternateIdentifier>
  </alternateIdentifiers>
  <formats>
    <format>application/vnd.openxmlformats-officedocument.spreadsheetml.sheet</format>
  </formats>
  <version>1.0</version>
  <contributors>
    <contributor contributorType="Editor">
      <contributorName>EarthChem Library (ECL)</contributorName>
      <nameIdentifier nameIdentifierScheme="DOI">10.17616/R3V644</nameIdentifier>
    </contributor>
  </contributors>
  <rightsList>
    <rights rightsURI="https://creativecommons.org/licenses/by/3.0/us/">Creative Commons Attribution-NonCommercial-Share Alike 3.0 United States [CC BY-NC-SA 3.0]</rights>
  </rightsList>
  <descriptions>
    <description descriptionType="Abstract">This is a summary of gas analyses from Shiveluch and Bezymianny volcanoes in 1960. Gas samples were collected from fumaroles at both volcanoes in 1960 and analyzed for major, minor elements and compounds by both O.G. Borisov and I.B. Nikitina of the USSR Science Academy.</description>
    <description descriptionType="Other">Russia, Kamchatka, Siberia, Shiveluch, Suelich Dome, Volcanic Gas, Fumarole Gas, Bezymianny</description>
  </descriptions>
  <geoLocations>
    <geoLocation>
      <geoLocationBox>55.939947 160.640744 56.653619 161.359794</geoLocationBox>
    </geoLocation>
    <geoLocation>
      <geoLocationPlace>Russia, Kamchatka, Siberia, Shiveluch volcano, Suelich Dome, Bezymianny volcano</geoLocationPlace>
    </geoLocation>
  </geoLocations>
</resource>
