<?xml version="1.0" encoding="UTF-8"?>
<mods xmlns="http://www.loc.gov/mods/v3"
      xmlns:xlink="http://www.w3.org/1999/xlink"
      xmlns:xsi="http://www.w3.org/2001/XMLSchema-instance"
      version="3.5"
      xsi:schemaLocation="http://www.loc.gov/mods/v3 http://www.loc.gov/standards/mods/v3/mods-3-5.xsd">
   <recordInfo>
      <recordIdentifier source="CoBA">OSGC-000-000-020-251</recordIdentifier>
      <recordCreationDate encoding="w3cdtf">2014-02-12</recordCreationDate>
      <recordChangeDate encoding="w3cdtf">2015-10-09</recordChangeDate>
      <recordContentSource>NCAR Library and Archives</recordContentSource>
      <recordOrigin>Human prepared. Transformed from a record in the OpenSky metadata
                framework.</recordOrigin>
      <recordOrigin>This record was transformed using the following
                files: osm-main-to-mods.xsl, osm-common-to-mods.xsl, and
                osm-article-to-mods.xsl.</recordOrigin>
      <languageOfCataloging>
         <languageTerm type="text">English</languageTerm>
         <languageTerm type="code" authority="iso639-2b">eng</languageTerm>
      </languageOfCataloging>
   </recordInfo>
   <titleInfo>
      <title>Historically grounded spatial population projections for the continental United States</title>
   </titleInfo>
   <name type="personal"
         valueURI="16072"
         authorityURI="https://people.ucar.edu"
         authority="UCAR People Database"
         usage="primary">
      <namePart type="given">Bryan</namePart>
      <namePart type="family">Jones</namePart>
      <displayForm>Bryan Jones</displayForm>
      <role>
         <roleTerm type="text" authority="marcrelator">author</roleTerm>
         <roleTerm type="code" authority="marcrelator">aut</roleTerm>
      </role>
      <affiliation>University Corporation For Atmospheric Research (UCAR):National Center for Atmospheric Research (NCAR):Integrated Science Program (ISP)</affiliation>
   </name>
   <name type="personal"
         valueURI="2497"
         authorityURI="https://people.ucar.edu"
         authority="UCAR People Database">
      <namePart type="given">Brian</namePart>
      <namePart type="given">C.</namePart>
      <namePart type="family">O'Neill</namePart>
      <displayForm>Brian C. O'Neill</displayForm>
      <role>
         <roleTerm type="text" authority="marcrelator">author</roleTerm>
         <roleTerm type="code" authority="marcrelator">aut</roleTerm>
      </role>
      <affiliation>University Corporation For Atmospheric Research (UCAR):National Center for Atmospheric Research (NCAR):NCAR Earth System Laboratory (NESL):Climate and Global Dynamics Division (CGD):Climate Change Research (CCR)</affiliation>
   </name>
   <typeOfResource>text</typeOfResource>
   <genre authority="marcgt">article</genre>
   <originInfo>
      <dateIssued encoding="w3cdtf" keyDate="yes">2013-12-01</dateIssued>
      <publisher>Institute of Physics Publishing</publisher>
   </originInfo>
   <language>
      <languageTerm type="code" authority="rfc5646">en</languageTerm>
   </language>
   <physicalDescription>
      <internetMediaType>application/pdf</internetMediaType>
   </physicalDescription>
   <abstract lang="eng">Large-scale spatial population projections are of growing importance to the global change community. Spatial settlement patterns are a key determinant of vulnerability to climate-related hazards as well as to land-use and its consequences for habitat, energy use, and emissions of greenhouse gases and air pollutants. Few projections exist of spatial distribution at national or larger scales, and while recent efforts improve on earlier approaches that simply scaled or extrapolated existing spatial patterns, important methodological shortcomings remain and models have not been calibrated to nor validated against historical trends. Here we present spatially explicit 100-year projections for the continental United States consistent with two different scenarios of possible socio-economic development. The projections are based on a new model that is calibrated to observed changes in regional population distribution since 1950, corrects for distorting effects at borders, and employs a spatial mask for designating protected or uninhabitable land. Using new metrics for comparing spatial outcomes, we find that our projections anticipate more moderate trends in urban expansion and coastal settlement than widely used existing projections. We also find that differences in outcomes across models are much larger than differences across alternative socio-economic scenarios for a given model, emphasizing the importance of better understanding of methods of spatial population projection for improved integrated assessments of social and environmental change.</abstract>
   <relatedItem type="host">
      <titleInfo>
         <title>Environmental Research Letters</title>
      </titleInfo>
      <part>
         <detail type="volume">
            <number>8</number>
         </detail>
         <detail type="issue">
            <number>4</number>
         </detail>
         <extent unit="pages">
            <total>11</total>
         </extent>
      </part>
   </relatedItem>
   <extension>
      <osm:classification xmlns:osm="http://nldr.library.ucar.edu/metadata/osm">Refereed</osm:classification>
   </extension>
   <extension>
      <osm:collaboration xmlns:osm="http://nldr.library.ucar.edu/metadata/osm">UCAR only</osm:collaboration>
   </extension>
   <extension>
      <osm:collectionKey xmlns:osm="http://nldr.library.ucar.edu/metadata/osm">articles</osm:collectionKey>
   </extension>
   <relatedItem type="isReferencedBy">
      <identifier type="uri">http://dx.doi.org/10.1088/1748-9326/8/4/044021</identifier>
   </relatedItem>
   <identifier type="uri" displayLabel="Legacy citable URL">http://nldr.library.ucar.edu/repository/collections/OSGC-000-000-020-251</identifier>
   <identifier type="doi">10.1088/1748-9326/8/4/044021</identifier>
   <accessCondition type="use and reproduction">Copyright Author(s) 2013. This work is distributed under the Creative Commons Attribution 3.0 License</accessCondition>
</mods>
