<dryad:DryadDataFile xmlns:dryad="http://purl.org/dryad/schema/terms/v3.1" xmlns:dcterms="http://purl.org/dc/terms/" xmlns:xsi="http://www.w3.org/2001/XMLSchema-instance" xsi:schemaLocation="http://purl.org/dryad/schema/terms/v3.1 http://datadryad.org/profile/v3.1/dryad.xsd">
  <dcterms:type>file</dcterms:type>
  <dcterms:creator>Namouchi, Amine</dcterms:creator>
  <dcterms:creator>Karboul, Anis</dcterms:creator>
  <dcterms:creator>Fabre, Michel</dcterms:creator>
  <dcterms:creator>Gutierrez, Maria Cristina</dcterms:creator>
  <dcterms:creator>Mardassi, Helmi</dcterms:creator>
  <dcterms:title>concatenated_PE3-PE4-PE_PGRS26-PE_PGRS35-PE_PGRS51-PE_PGRS62</dcterms:title>
  <dcterms:identifier>http://dx.doi.org/10.5061/dryad.c8jg8/7</dcterms:identifier>
  <dcterms:rights>http://creativecommons.org/publicdomain/zero/1.0/</dcterms:rights>
  <dcterms:dateSubmitted>2013-06-04T16:48:37Z</dcterms:dateSubmitted>
  <dcterms:available>2013-06-05T19:35:19Z</dcterms:available>
  <dcterms:provenance>Made available in DSpace on 2013-06-04T16:48:37Z (GMT). No. of bitstreams: 1
concatenated_PE3-PE4-PE_PGRS26-PE_PGRS35-PE_PGRS51-PE_PGRS62.txt: 72978 bytes, checksum: a01ff5061485d2bca21af7960f81ff73 (MD5)</dcterms:provenance>
  <dcterms:isPartOf>http://dx.doi.org/10.5061/dryad.c8jg8</dcterms:isPartOf>
</dryad:DryadDataFile>