<dryad:DryadDataFile xmlns:dryad="http://purl.org/dryad/schema/terms/v3.1" xmlns:dcterms="http://purl.org/dc/terms/" xmlns:dwc="http://rs.tdwg.org/dwc/terms/" xmlns:xsi="http://www.w3.org/2001/XMLSchema-instance" xsi:schemaLocation="http://purl.org/dryad/schema/terms/v3.1 http://datadryad.org/profile/v3.1/dryad.xsd">
  <dcterms:type>file</dcterms:type>
  <dcterms:creator>Faircloth, Brant C.</dcterms:creator>
  <dcterms:creator>Branstetter, Michael G.</dcterms:creator>
  <dcterms:creator>White, Noor D.</dcterms:creator>
  <dcterms:creator>Brady, S&#233;an G.</dcterms:creator>
  <dcterms:title>pycogent-distance-estimates.xlsx</dcterms:title>
  <dcterms:identifier>http://dx.doi.org/10.5061/dryad.46195/26</dcterms:identifier>
  <dcterms:rights>http://creativecommons.org/publicdomain/zero/1.0/</dcterms:rights>
  <dcterms:description>Distances estimates output by PyCogent as xlsx file.</dcterms:description>
  <dcterms:subject>ultraconserved elements</dcterms:subject>
  <dcterms:subject>UCEs</dcterms:subject>
  <dcterms:subject>target enrichment</dcterms:subject>
  <dcterms:subject>baits</dcterms:subject>
  <dcterms:subject>probes</dcterms:subject>
  <dcterms:subject>arthropods</dcterms:subject>
  <dcterms:subject>conserved sequence</dcterms:subject>
  <dwc:scientificName>Acordulecera pellucida</dwc:scientificName>
  <dwc:scientificName>Andrena (Callandrena) asteris</dwc:scientificName>
  <dwc:scientificName>Andrena (Melandrena) sp</dwc:scientificName>
  <dwc:scientificName>Aphaenogaster albisetosa</dwc:scientificName>
  <dwc:scientificName>Aphaenogaster megommata</dwc:scientificName>
  <dwc:scientificName>Aphaenogaster tennesseensis</dwc:scientificName>
  <dwc:scientificName>Aphaenogaster texana</dwc:scientificName>
  <dwc:scientificName>Aporus niger</dwc:scientificName>
  <dwc:scientificName>Bombus pensylvanicus</dwc:scientificName>
  <dwc:scientificName>Chalybion californicus</dwc:scientificName>
  <dwc:scientificName>Chyphotes mellipes</dwc:scientificName>
  <dwc:scientificName>Evaniella semaeoda</dwc:scientificName>
  <dwc:scientificName>Messor piceus</dwc:scientificName>
  <dwc:scientificName>Metapolybia cingulata</dwc:scientificName>
  <dwc:scientificName>Mischocyttarus flavitarsis</dwc:scientificName>
  <dwc:scientificName>Nasonia vitripennis</dwc:scientificName>
  <dwc:scientificName>Nematus tibialis</dwc:scientificName>
  <dwc:scientificName>Orthogonalys pulchella</dwc:scientificName>
  <dwc:scientificName>Pogonomyrmex occidentalis</dwc:scientificName>
  <dwc:scientificName>Sapyga pumila</dwc:scientificName>
  <dwc:scientificName>Scolia verticalis</dwc:scientificName>
  <dwc:scientificName>Sericomyrmex sp</dwc:scientificName>
  <dwc:scientificName>Stenamma diecki</dwc:scientificName>
  <dwc:scientificName>Stenamma expolitum</dwc:scientificName>
  <dwc:scientificName>Stenamma felixi</dwc:scientificName>
  <dwc:scientificName>Stenamma impar</dwc:scientificName>
  <dwc:scientificName>Stenamma megamanni</dwc:scientificName>
  <dwc:scientificName>Stenamma muralla</dwc:scientificName>
  <dwc:scientificName>Taxonus pallidicornis</dwc:scientificName>
  <dwc:scientificName>Acromyrmex echinatior</dwc:scientificName>
  <dwc:scientificName>Apis mellifera</dwc:scientificName>
  <dwc:scientificName>Atta cephalotes</dwc:scientificName>
  <dwc:scientificName>Camponotus floridanus</dwc:scientificName>
  <dwc:scientificName>Cerapachys biroi</dwc:scientificName>
  <dwc:scientificName>Ceratosolen solmsi</dwc:scientificName>
  <dwc:scientificName>Harpegnathos saltator</dwc:scientificName>
  <dwc:scientificName>Lasioglossum albipes</dwc:scientificName>
  <dwc:scientificName>Linepithema humile</dwc:scientificName>
  <dwc:scientificName>Nasonia giraulti</dwc:scientificName>
  <dwc:scientificName>Nasonia longicornis</dwc:scientificName>
  <dwc:scientificName>Pogonomyrmex barbatus</dwc:scientificName>
  <dwc:scientificName>Solenopsis invicta</dwc:scientificName>
  <dwc:scientificName>Hymenoptera</dwc:scientificName>
  <dcterms:dateSubmitted>2014-09-19T21:50:00Z</dcterms:dateSubmitted>
  <dcterms:available>2014-09-19T22:07:40Z</dcterms:available>
  <dcterms:format>67020</dcterms:format>
  <dcterms:provenance>Made available in DSpace on 2014-09-19T21:50:00Z (GMT). No. of bitstreams: 1
pycogent-distance-estimates.xlsx: 67020 bytes, checksum: d6858e24ccc829c975218765cff7f663 (MD5)</dcterms:provenance>
  <dcterms:isPartOf>http://dx.doi.org/10.5061/dryad.46195</dcterms:isPartOf>
</dryad:DryadDataFile>